xpt2csv/__init__.py
xpt2csv/to_csv.py
xpt2csv_cli-0.1.4.dist-info/METADATA
xpt2csv_cli-0.1.4.dist-info/WHEEL
xpt2csv_cli-0.1.4.dist-info/entry_points.txt
xpt2csv_cli-0.1.4.dist-info/top_level.txt
xpt2csv_cli-0.1.4.dist-info/RECORD
