Metadata-Version: 2.1
Name: xpt2csv-cli
Version: 0.1.4
Summary: CLI app to convert xpt file to csv
Author: Yousuf Ali
Project-URL: Source, https://github.com/Yousuf28/xpt2csv
Project-URL: Tracker, https://github.com/Yousuf28/xpt2csv/issues
Requires-Dist: pyreadstat
Requires-Dist: click
